mg400control/__init__.py
mg400control/ros2_mg400_control_00.py
mg400control-0.0.4.dist-info/LICENSE.txt
mg400control-0.0.4.dist-info/METADATA
mg400control-0.0.4.dist-info/WHEEL
mg400control-0.0.4.dist-info/top_level.txt
mg400control-0.0.4.dist-info/RECORD
